LICENSE.md
README.md
setup.py
MAP/__init__.py
MAP/map_generator.py
MAP/AI/__init__.py
MAP/AI/text_generator.py
MAP/AI/data/char_to_idx.pickle
MAP/AI/data/entire_model.pt
MAP/AI/data/idx_to_char.pickle
MAP/AI/data/text.txt
MAP/data/map.json
TEMPLECMD.egg-info/PKG-INFO
TEMPLECMD.egg-info/SOURCES.txt
TEMPLECMD.egg-info/dependency_links.txt
TEMPLECMD.egg-info/entry_points.txt
TEMPLECMD.egg-info/requires.txt
TEMPLECMD.egg-info/top_level.txt
TUI/__init__.py
TUI/__main__.py
TUI/intro.py
TUI/lose.py
TUI/main_hero_class.py
TUI/map_output.py
TUI/outro.py
TUI/quests.py
TUI/words.py
TUI/data/helpstr.json
TUI/data/icon.ico
TUI/data/intro.jpg
TUI/data/intro.json
TUI/data/lose.jpg
TUI/data/outro.jpg
TUI/saves/.gitkeep