Metadata-Version: 1.2
Name: TEMPLECMD
Version: 1.6
Summary: Текстовый квест по мотивам книги Г. Лавкрафта "ХРАМ"
Home-page: https://github.com/shasoka/TxtQUEST
Author: shasoka
Author-email: shenbergarkadii@gmail.com
Maintainer: infern397
Maintainer-email: Semenmochalov@gmail.com
License: UNKNOWN
Platform: UNKNOWN
